pynetbox/__init__.py
pynetbox/core/__init__.py
pynetbox/core/api.py
pynetbox/core/app.py
pynetbox/core/endpoint.py
pynetbox/core/query.py
pynetbox/core/response.py
pynetbox/core/util.py
pynetbox/models/__init__.py
pynetbox/models/circuits.py
pynetbox/models/dcim.py
pynetbox/models/extras.py
pynetbox/models/ipam.py
pynetbox/models/users.py
pynetbox/models/virtualization.py
pynetbox/models/wireless.py
pynetbox_paulexyz-6.6.2.post1.dist-info/LICENSE
pynetbox_paulexyz-6.6.2.post1.dist-info/METADATA
pynetbox_paulexyz-6.6.2.post1.dist-info/WHEEL
pynetbox_paulexyz-6.6.2.post1.dist-info/top_level.txt
pynetbox_paulexyz-6.6.2.post1.dist-info/RECORD
